slippage_tabulator/V2.py
slippage_tabulator/V3.py
slippage_tabulator/__init__.py
slippage_tabulator/main.py
slippage_tabulator/test.py
slippage_tabulator/uniswap_main.py
slippage_tabulator-0.3.0.dist-info/LICENSE
slippage_tabulator-0.3.0.dist-info/WHEEL
slippage_tabulator-0.3.0.dist-info/METADATA
slippage_tabulator-0.3.0.dist-info/RECORD
